[
  {
    "index": 0,
    "papers": [
      {
        "key": "marigliano2024glucose",
        "author": "Marigliano, Marco and Piona, Claudia and Mancioppi, Valentina and Morotti, Elisa and Morandi, Anita and Maffeis, Claudio",
        "title": "Glucose sensor with predictive alarm for hypoglycaemia: Improved glycaemic control in adolescents with type 1 diabetes"
      }
    ]
  },
  {
    "index": 1,
    "papers": [
      {
        "key": "vettoretti2020advanced",
        "author": "Vettoretti, Martina and Cappon, Giacomo and Facchinetti, Andrea and Sparacino, Giovanni",
        "title": "Advanced diabetes management using artificial intelligence and continuous glucose monitoring sensors"
      }
    ]
  },
  {
    "index": 2,
    "papers": [
      {
        "key": "shroff2023glucoseassist",
        "author": "Shroff, Prisha and Arefeen, Asiful and Ghasemzadeh, Hassan",
        "title": "GlucoseAssist: Personalized Blood Glucose Level Predictions and Early Dysglycemia Detection"
      }
    ]
  },
  {
    "index": 3,
    "papers": [
      {
        "key": "arefeen2022forewarning",
        "author": "Arefeen, Asiful and Fessler, Samantha and Johnston, Carol and Ghasemzadeh, Hassan",
        "title": "Forewarning postprandial hyperglycemia with interpretations using machine learning"
      }
    ]
  },
  {
    "index": 4,
    "papers": [
      {
        "key": "zhu2022personalized",
        "author": "Zhu, Taiyu and Li, Kezhi and Herrero, Pau and Georgiou, Pantelis",
        "title": "Personalized blood glucose prediction for type 1 diabetes using evidential deep learning and meta-learning"
      }
    ]
  },
  {
    "index": 5,
    "papers": [
      {
        "key": "keren2016convolutional",
        "author": "Keren, Gil and Schuller, Bj{\\\"o}rn",
        "title": "Convolutional RNN: an enhanced model for extracting features from sequential data"
      }
    ]
  },
  {
    "index": 6,
    "papers": [
      {
        "key": "li2019convolutional",
        "author": "Li, Kezhi and Daniels, John and Liu, Chengyuan and Herrero, Pau and Georgiou, Pantelis",
        "title": "Convolutional recurrent neural networks for glucose prediction"
      }
    ]
  },
  {
    "index": 7,
    "papers": [
      {
        "key": "li2021survey",
        "author": "Li, Zewen and Liu, Fan and Yang, Wenjie and Peng, Shouheng and Zhou, Jun",
        "title": "A survey of convolutional neural networks: analysis, applications, and prospects"
      }
    ]
  },
  {
    "index": 8,
    "papers": [
      {
        "key": "medsker2001recurrent",
        "author": "Medsker, Larry R and Jain, Lakhmi and others",
        "title": "Recurrent neural networks"
      }
    ]
  },
  {
    "index": 9,
    "papers": [
      {
        "key": "hochreiter1997long",
        "author": "Hochreiter, Sepp and Schmidhuber, J{\\\"u}rgen",
        "title": "Long short-term memory"
      }
    ]
  },
  {
    "index": 10,
    "papers": [
      {
        "key": "aliberti2019multi",
        "author": "Aliberti, Alessandro and Pupillo, Irene and Terna, Stefano and Macii, Enrico and Di Cataldo, Santa and Patti, Edoardo and Acquaviva, Andrea",
        "title": "A multi-patient data-driven approach to blood glucose prediction"
      }
    ]
  },
  {
    "index": 11,
    "papers": [
      {
        "key": "billings2013nonlinear",
        "author": "Billings, Stephen A",
        "title": "Nonlinear system identification: NARMAX methods in the time, frequency, and spatio-temporal domains"
      }
    ]
  },
  {
    "index": 12,
    "papers": [
      {
        "key": "sun2018predicting",
        "author": "Sun, Qingnan and Jankovic, Marko V and Bally, Lia and Mougiakakou, Stavroula G",
        "title": "Predicting blood glucose with an lstm and bi-lstm based deep neural network"
      }
    ]
  },
  {
    "index": 13,
    "papers": [
      {
        "key": "butt2023feature",
        "author": "Butt, Hatim and Khosa, Ikramullah and Iftikhar, Muhammad Aksam",
        "title": "Feature transformation for efficient blood glucose prediction in type 1 diabetes mellitus patients"
      }
    ]
  },
  {
    "index": 14,
    "papers": [
      {
        "key": "zhang2021deep",
        "author": "Zhang, Meng and Flores, Kevin B and Tran, Hien T",
        "title": "Deep learning and regression approaches to forecasting blood glucose levels for type 1 diabetes"
      }
    ]
  },
  {
    "index": 15,
    "papers": [
      {
        "key": "zhang2021deep",
        "author": "Zhang, Meng and Flores, Kevin B and Tran, Hien T",
        "title": "Deep learning and regression approaches to forecasting blood glucose levels for type 1 diabetes"
      }
    ]
  }
]