[
  {
    "index": 0,
    "papers": [
      {
        "key": "",
        "author": "Unknown",
        "title": "Unknown"
      }
    ]
  },
  {
    "index": 1,
    "papers": [
      {
        "key": "10.5555/3540261.3541519",
        "author": "von K\\\"{u}gelgen, Julius and Sharma, Yash and Gresele, Luigi and Brendel, Wieland and Sch\\\"{o}lkopf, Bernhard and Besserve, Michel and Locatello, Francesco",
        "title": "Self-supervised learning with data augmentations provably isolates content from style"
      }
    ]
  },
  {
    "index": 2,
    "papers": [
      {
        "key": "pmlr-v206-morioka23a",
        "author": "Morioka, Hiroshi and Hyvarinen, Aapo",
        "title": "Connectivity-contrastive learning: Combining causal discovery and representation learning for multimodal data"
      },
      {
        "key": "daunhawer2023identifiability",
        "author": "Imant Daunhawer and Alice Bizeul and Emanuele Palumbo and Alexander Marx and Julia E Vogt",
        "title": "Identifiability Results for Multimodal Contrastive Learning"
      }
    ]
  },
  {
    "index": 3,
    "papers": [
      {
        "key": "guo2024outofvariable",
        "author": "Siyuan Guo and Jonas Bernhard Wildberger and Bernhard Sch{\\\"o}lkopf",
        "title": "Out-of-Variable Generalisation for Discriminative Models"
      }
    ]
  },
  {
    "index": 4,
    "papers": [
      {
        "key": "10.1007/978-3-030-71704-9_65",
        "author": "Farahani, Abolfazl\nand Voghoei, Sahar\nand Rasheed, Khaled\nand Arabnia, Hamid R.",
        "title": "A Brief Review of Domain Adaptation"
      },
      {
        "key": "article",
        "author": "Liu, Xiaofeng and Yoo, Chaehwa and Xing, Fangxu and Oh, Hyejin and Fakhri, Georges and Kang, Je-Won and Woo, Jonghye",
        "title": "Deep Unsupervised Domain Adaptation: A Review of Recent Advances and Perspectives"
      }
    ]
  },
  {
    "index": 5,
    "papers": [
      {
        "key": "8100115",
        "author": "Isola, Phillip and Zhu, Jun-Yan and Zhou, Tinghui and Efros, Alexei A.",
        "title": "Image-to-Image Translation with Conditional Adversarial Networks"
      },
      {
        "key": "9010872",
        "author": "Lin, Yu-Jing and Wu, Po-Wei and Chang, Che-Han and Chang, Edward and Liao, Shih-Wei",
        "title": "RelGAN: Multi-Domain Image-to-Image Translation via Relative Attributes"
      }
    ]
  },
  {
    "index": 6,
    "papers": [
      {
        "key": "NEURIPS2018_39e98420",
        "author": "Magliacane, Sara and van Ommen, Thijs and Claassen, Tom and Bongers, Stephan and Versteeg, Philip and Mooij, Joris M",
        "title": "Domain Adaptation by Using Causal Inference to Predict Invariant Conditional Distributions"
      }
    ]
  },
  {
    "index": 7,
    "papers": [
      {
        "key": "10.5555/3524938.3525815",
        "author": "Teshima, Takeshi and Sato, Issei and Sugiyama, Masashi",
        "title": "Few-shot domain adaptation by causal mechanism transfer"
      }
    ]
  },
  {
    "index": 8,
    "papers": [
      {
        "key": "Zhang_Gong_Schoelkopf_2015",
        "author": "Zhang, Kun and Gong, Mingming and Schoelkopf, Bernhard",
        "title": "Multi-Source Domain Adaptation: A Causal View"
      }
    ]
  }
]