[
  {
    "index": 0,
    "papers": [
      {
        "key": "chen2020defining",
        "author": "Chen, Jiachi and Xia, Xin and Lo, David and Grundy, John and Luo, Xiapu and Chen, Ting",
        "title": "Defining smart contract defects on ethereum"
      }
    ]
  },
  {
    "index": 1,
    "papers": [
      {
        "key": "stackExchange",
        "author": "Unknown",
        "title": "stackExchange"
      }
    ]
  },
  {
    "index": 2,
    "papers": [
      {
        "key": "chen2021defectchecker",
        "author": "Chen, Jiachi and Xia, Xin and Lo, David and Grundy, John and Luo, Xiapu and Chen, Ting",
        "title": "Defectchecker: Automated smart contract defect detection by analyzing evm bytecode"
      }
    ]
  },
  {
    "index": 3,
    "papers": [
      {
        "key": "hu2023detect",
        "author": "Hu, Tianyuan and Li, Bixin and Pan, Zhenyu and Qian, Chen",
        "title": "Detect defects of solidity smart contract based on the knowledge graph"
      }
    ]
  },
  {
    "index": 4,
    "papers": [
      {
        "key": "luu2016making",
        "author": "Luu, Loi and Chu, Duc-Hiep and Olickel, Hrishi and Saxena, Prateek and Hobor, Aquinas",
        "title": "Making smart contracts smarter"
      }
    ]
  },
  {
    "index": 5,
    "papers": [
      {
        "key": "de2008z3",
        "author": "De Moura, Leonardo and Bj{\\o}rner, Nikolaj",
        "title": "Z3: An efficient SMT solver"
      }
    ]
  },
  {
    "index": 6,
    "papers": [
      {
        "key": "nikolic2018finding",
        "author": "Nikoli{\\'c}, Ivica and Kolluri, Aashish and Sergey, Ilya and Saxena, Prateek and Hobor, Aquinas",
        "title": "Finding the greedy, prodigal, and suicidal contracts at scale"
      }
    ]
  },
  {
    "index": 7,
    "papers": [
      {
        "key": "rao2012sailfish",
        "author": "Rao, Sriram and Ramakrishnan, Raghu and Silberstein, Adam and Ovsiannikov, Mike and Reeves, Damian",
        "title": "Sailfish: A framework for large scale data processing"
      }
    ]
  },
  {
    "index": 8,
    "papers": [
      {
        "key": "mythril",
        "author": "Unknown",
        "title": "Mythril"
      }
    ]
  },
  {
    "index": 9,
    "papers": [
      {
        "key": "feist2019slither",
        "author": "Feist, Josselin and Grieco, Gustavo and Groce, Alex",
        "title": "Slither: a static analysis framework for smart contracts"
      }
    ]
  },
  {
    "index": 10,
    "papers": [
      {
        "key": "yang2023definition",
        "author": "Yang, Shuo and Chen, Jiachi and Zheng, Zibin",
        "title": "Definition and detection of defects in NFT smart contracts"
      }
    ]
  },
  {
    "index": 11,
    "papers": [
      {
        "key": "zhong2024prettysmart",
        "author": "Zhong, Zhijie and Zheng, Zibin and Dai, Hong-Ning and Xue, Qing and Chen, Junjia and Nan, Yuhong",
        "title": "PrettySmart: Detecting Permission Re-delegation Vulnerability for Token Behaviors in Smart Contracts"
      }
    ]
  },
  {
    "index": 12,
    "papers": [
      {
        "key": "jiang2018contractfuzzer",
        "author": "Jiang, Bo and Liu, Ye and Chan, Wing Kwong",
        "title": "Contractfuzzer: Fuzzing smart contracts for vulnerability detection"
      }
    ]
  },
  {
    "index": 13,
    "papers": [
      {
        "key": "grieco2020echidna",
        "author": "Grieco, Gustavo and Song, Will and Cygan, Artur and Feist, Josselin and Groce, Alex",
        "title": "Echidna: effective, usable, and fast fuzzing for smart contracts"
      }
    ]
  },
  {
    "index": 14,
    "papers": [
      {
        "key": "nguyen2020sfuzz",
        "author": "Nguyen, Tai D and Pham, Long H and Sun, Jun and Lin, Yun and Minh, Quang Tran",
        "title": "sfuzz: An efficient adaptive fuzzer for solidity smart contracts"
      }
    ]
  },
  {
    "index": 15,
    "papers": [
      {
        "key": "choi2021smartian",
        "author": "Choi, Jaeseung and Kim, Doyeon and Kim, Soomin and Grieco, Gustavo and Groce, Alex and Cha, Sang Kil",
        "title": "Smartian: Enhancing smart contract fuzzing with static and dynamic data-flow analyses"
      }
    ]
  },
  {
    "index": 16,
    "papers": [
      {
        "key": "guidi2022sleepminting",
        "author": "Guidi, Barbara and Michienzi, Andrea",
        "title": "Sleepminting, the brand new frontier of Non Fungible Tokens fraud"
      }
    ]
  },
  {
    "index": 17,
    "papers": [
      {
        "key": "guidi2023delving",
        "author": "Guidi, Barbara and Michienzi, Andrea",
        "title": "Delving NFT vulnerabilities, a sleepminting prevention system"
      }
    ]
  }
]