[
  {
    "index": 0,
    "papers": [
      {
        "key": "hochreiter1997long",
        "author": "Hochreiter, Sepp and Schmidhuber, J{\\\"u}rgen",
        "title": "Long short-term memory"
      }
    ]
  },
  {
    "index": 1,
    "papers": [
      {
        "key": "lecun1995convolutional",
        "author": "LeCun, Yann and Bengio, Yoshua and others",
        "title": "Convolutional networks for images, speech, and time series"
      }
    ]
  },
  {
    "index": 2,
    "papers": [
      {
        "key": "vaswani2017attention",
        "author": "Vaswani, Ashish and Shazeer, Noam and Parmar, Niki and Uszkoreit, Jakob and Jones, Llion and Gomez, Aidan N and Kaiser, {\\L}ukasz and Polosukhin, Illia",
        "title": "Attention is all you need"
      }
    ]
  },
  {
    "index": 3,
    "papers": [
      {
        "key": "wen2023transformers",
        "author": "Wen, Qingsong and Zhou, Tian and Zhang, Chaoli and Chen, Weiqi and Ma, Ziqing and Yan, Junchi and Sun, Liang",
        "title": "Transformers in time series: A survey"
      }
    ]
  },
  {
    "index": 4,
    "papers": [
      {
        "key": "li2023time",
        "author": "Li, Shaohan and Jin, Xiaoping and Xuan, Yong and Zhou, Xiang and Chen, Wenhu and Wang, Yu-Xiang and Yan, Xifeng",
        "title": "Time series forecasting with transformers: A survey"
      }
    ]
  },
  {
    "index": 5,
    "papers": [
      {
        "key": "lim2021temporal",
        "author": "Lim, Bryan and Ar{\\i}k, Sercan {\\\"O} and Loeff, Nicolas and Pfister, Tomas",
        "title": "Temporal fusion transformers for interpretable multi-horizon time series forecasting"
      },
      {
        "key": "zhou2021informer",
        "author": "Zhou, Haoyi and Zhang, Shanghang and Peng, Jieqi and Zhang, Shuai and Li, Jianxin and Xiong, Hui and Zhang, Wancai",
        "title": "Informer: Beyond efficient transformer for long sequence time-series forecasting"
      }
    ]
  },
  {
    "index": 6,
    "papers": [
      {
        "key": "box2015time",
        "author": "Box, George EP and Jenkins, Gwilym M and Reinsel, Gregory C and Ljung, Greta M",
        "title": "Time series analysis: forecasting and control"
      }
    ]
  },
  {
    "index": 7,
    "papers": [
      {
        "key": "hyndman2018forecasting",
        "author": "Hyndman, Rob J and Athanasopoulos, George",
        "title": "Forecasting: principles and practice"
      }
    ]
  },
  {
    "index": 8,
    "papers": [
      {
        "key": "wu2021autoformer",
        "author": "Wu, Haixu and Xu, Jiehui and Wang, Jianmin and Long, Mingsheng",
        "title": "Autoformer: Decomposition transformers with auto-correlation for long-term series forecasting"
      }
    ]
  },
  {
    "index": 9,
    "papers": [
      {
        "key": "zerveas2021transformer",
        "author": "Zerveas, George and Jayaraman, Srideepika and Patel, Dhaval and Bhamidipaty, Anuradha and Eickhoff, Carsten",
        "title": "A transformer-based framework for multivariate time series representation learning"
      }
    ]
  },
  {
    "index": 10,
    "papers": [
      {
        "key": "zerveas2021transformer",
        "author": "Zerveas, George and Jayaraman, Srideepika and Patel, Dhaval and Bhamidipaty, Anuradha and Eickhoff, Carsten",
        "title": "A transformer-based framework for multivariate time series representation learning"
      }
    ]
  },
  {
    "index": 11,
    "papers": [
      {
        "key": "cordonnier2021differentiable",
        "author": "Cordonnier, Jean-Baptiste and Mahendran, Aravindh and Dosovitskiy, Alexey and Weissenborn, Dirk and Uszkoreit, Jakob and Unterthiner, Thomas",
        "title": "Differentiable patch selection for image recognition"
      }
    ]
  },
  {
    "index": 12,
    "papers": [
      {
        "key": "vaswani2017attention",
        "author": "Vaswani, Ashish and Shazeer, Noam and Parmar, Niki and Uszkoreit, Jakob and Jones, Llion and Gomez, Aidan N and Kaiser, {\\L}ukasz and Polosukhin, Illia",
        "title": "Attention is all you need"
      }
    ]
  },
  {
    "index": 13,
    "papers": [
      {
        "key": "shaw2018self",
        "author": "Shaw, Peter and Uszkoreit, Jakob and Vaswani, Ashish",
        "title": "Self-attention with relative position representations"
      }
    ]
  },
  {
    "index": 14,
    "papers": [
      {
        "key": "foumani2024improving",
        "author": "Foumani, Navid Mohammadi and Tan, Chang Wei and Webb, Geoffrey I and Salehi, Mahsa",
        "title": "Improving position encoding of transformers for multivariate time series classification"
      }
    ]
  },
  {
    "index": 15,
    "papers": [
      {
        "key": "vaswani2017attention",
        "author": "Vaswani, Ashish and Shazeer, Noam and Parmar, Niki and Uszkoreit, Jakob and Jones, Llion and Gomez, Aidan N and Kaiser, {\\L}ukasz and Polosukhin, Illia",
        "title": "Attention is all you need"
      }
    ]
  },
  {
    "index": 16,
    "papers": [
      {
        "key": "vaswani2017attention",
        "author": "Vaswani, Ashish and Shazeer, Noam and Parmar, Niki and Uszkoreit, Jakob and Jones, Llion and Gomez, Aidan N and Kaiser, {\\L}ukasz and Polosukhin, Illia",
        "title": "Attention is all you need"
      }
    ]
  },
  {
    "index": 17,
    "papers": [
      {
        "key": "shaw2018self",
        "author": "Shaw, Peter and Uszkoreit, Jakob and Vaswani, Ashish",
        "title": "Self-attention with relative position representations"
      }
    ]
  },
  {
    "index": 18,
    "papers": [
      {
        "key": "foumani2024improving",
        "author": "Foumani, Navid Mohammadi and Tan, Chang Wei and Webb, Geoffrey I and Salehi, Mahsa",
        "title": "Improving position encoding of transformers for multivariate time series classification"
      }
    ]
  },
  {
    "index": 19,
    "papers": [
      {
        "key": "foumani2024improving",
        "author": "Foumani, Navid Mohammadi and Tan, Chang Wei and Webb, Geoffrey I and Salehi, Mahsa",
        "title": "Improving position encoding of transformers for multivariate time series classification"
      }
    ]
  },
  {
    "index": 20,
    "papers": [
      {
        "key": "ke2020rethinking",
        "author": "Ke, Guolin and He, Di and Liu, Tie-Yan",
        "title": "Rethinking positional encoding in language pre-training"
      }
    ]
  },
  {
    "index": 21,
    "papers": [
      {
        "key": "liutkus2021relative",
        "author": "Liutkus, Antoine and C{\\i}fka, Ond{\\v{r}}ej and Wu, Shih-Lun and Simsekli, Umut and Yang, Yi-Hsuan and Richard, Gael",
        "title": "Relative positional encoding for transformers with linear complexity"
      }
    ]
  },
  {
    "index": 22,
    "papers": [
      {
        "key": "zhang2024intriguing",
        "author": "Zhang, Jianqi and Wang, Jingyao and Qiang, Wenwen and Xu, Fanjiang and Zheng, Changwen and Sun, Fuchun and Xiong, Hui",
        "title": "Intriguing Properties of Positional Encoding in Time Series Forecasting"
      }
    ]
  }
]