[
  {
    "index": 0,
    "papers": [
      {
        "key": "ho2020denoising",
        "author": "Ho, Jonathan and Jain, Ajay and Abbeel, Pieter",
        "title": "Denoising diffusion probabilistic models"
      }
    ]
  },
  {
    "index": 1,
    "papers": [
      {
        "key": "song2020score",
        "author": "Song, Yang and Sohl-Dickstein, Jascha and Kingma, Diederik P and Kumar, Abhishek and Ermon, Stefano and Poole, Ben",
        "title": "Score-based generative modeling through stochastic differential equations"
      },
      {
        "key": "ho2020denoising",
        "author": "Ho, Jonathan and Jain, Ajay and Abbeel, Pieter",
        "title": "Denoising diffusion probabilistic models"
      }
    ]
  },
  {
    "index": 2,
    "papers": [
      {
        "key": "song2020denoising",
        "author": "Song, Jiaming and Meng, Chenlin and Ermon, Stefano",
        "title": "Denoising diffusion implicit models"
      }
    ]
  },
  {
    "index": 3,
    "papers": [
      {
        "key": "saharia2022palette",
        "author": "Saharia, Chitwan and Chan, William and Chang, Huiwen and Lee, Chris and Ho, Jonathan and Salimans, Tim and Fleet, David and Norouzi, Mohammad",
        "title": "Palette: Image-to-image diffusion models"
      },
      {
        "key": "lugmayr2022repaint",
        "author": "Lugmayr, Andreas and Danelljan, Martin and Romero, Andres and Yu, Fisher and Timofte, Radu and Van Gool, Luc",
        "title": "Repaint: Inpainting using denoising diffusion probabilistic models"
      }
    ]
  },
  {
    "index": 4,
    "papers": [
      {
        "key": "nichol2021glide",
        "author": "Nichol, Alex and Dhariwal, Prafulla and Ramesh, Aditya and Shyam, Pranav and Mishkin, Pamela and McGrew, Bob and Sutskever, Ilya and Chen, Mark",
        "title": "Glide: Towards photorealistic image generation and editing with text-guided diffusion models"
      },
      {
        "key": "brooks2023instructpix2pix",
        "author": "Brooks, Tim and Holynski, Aleksander and Efros, Alexei A",
        "title": "Instructpix2pix: Learning to follow image editing instructions"
      }
    ]
  },
  {
    "index": 5,
    "papers": [
      {
        "key": "qi2024deadiff",
        "author": "Qi, Tianhao and Fang, Shancheng and Wu, Yanze and Xie, Hongtao and Liu, Jiawei and Chen, Lang and He, Qian and Zhang, Yongdong",
        "title": "DEADiff: An Efficient Stylization Diffusion Model with Disentangled Representations"
      }
    ]
  },
  {
    "index": 6,
    "papers": [
      {
        "key": "dhariwal2021diffusion",
        "author": "Dhariwal, Prafulla and Nichol, Alexander",
        "title": "Diffusion models beat gans on image synthesis"
      }
    ]
  },
  {
    "index": 7,
    "papers": [
      {
        "key": "song2020score",
        "author": "Song, Yang and Sohl-Dickstein, Jascha and Kingma, Diederik P and Kumar, Abhishek and Ermon, Stefano and Poole, Ben",
        "title": "Score-based generative modeling through stochastic differential equations"
      }
    ]
  },
  {
    "index": 8,
    "papers": [
      {
        "key": "song2020denoising",
        "author": "Song, Jiaming and Meng, Chenlin and Ermon, Stefano",
        "title": "Denoising diffusion implicit models"
      }
    ]
  },
  {
    "index": 9,
    "papers": [
      {
        "key": "rombach2022high",
        "author": "Rombach, Robin and Blattmann, Andreas and Lorenz, Dominik and Esser, Patrick and Ommer, Bj{\\\"o}rn",
        "title": "High-resolution image synthesis with latent diffusion models"
      }
    ]
  },
  {
    "index": 10,
    "papers": [
      {
        "key": "rombach2022high",
        "author": "Rombach, Robin and Blattmann, Andreas and Lorenz, Dominik and Esser, Patrick and Ommer, Bj{\\\"o}rn",
        "title": "High-resolution image synthesis with latent diffusion models"
      }
    ]
  },
  {
    "index": 11,
    "papers": [
      {
        "key": "al2007combined",
        "author": "Al-Haj, Ali",
        "title": "Combined DWT-DCT digital image watermarking"
      }
    ]
  },
  {
    "index": 12,
    "papers": [
      {
        "key": "liu2002svd",
        "author": "Liu, Ruizhen and Tan, Tieniu",
        "title": "An SVD-based watermarking scheme for protecting rightful ownership"
      }
    ]
  },
  {
    "index": 13,
    "papers": [
      {
        "key": "zhu2018hidden",
        "author": "Zhu, Jiren and Kaplan, Russell and Johnson, Justin and Fei-Fei, Li",
        "title": "Hidden: Hiding data with deep networks"
      }
    ]
  },
  {
    "index": 14,
    "papers": [
      {
        "key": "tancik2020stegastamp",
        "author": "Tancik, Matthew and Mildenhall, Ben and Ng, Ren",
        "title": "Stegastamp: Invisible hyperlinks in physical photographs"
      }
    ]
  },
  {
    "index": 15,
    "papers": [
      {
        "key": "bui2023rosteals",
        "author": "Bui, Tu and Agarwal, Shruti and Yu, Ning and Collomosse, John",
        "title": "Rosteals: Robust steganography using autoencoder latent space"
      }
    ]
  },
  {
    "index": 16,
    "papers": [
      {
        "key": "zhao2023recipe",
        "author": "Zhao, Yunqing and Pang, Tianyu and Du, Chao and Yang, Xiao and Cheung, Ngai-Man and Lin, Min",
        "title": "A recipe for watermarking diffusion models"
      }
    ]
  },
  {
    "index": 17,
    "papers": [
      {
        "key": "fernandez2023stable",
        "author": "Fernandez, Pierre and Couairon, Guillaume and J{\\'e}gou, Herv{\\'e} and Douze, Matthijs and Furon, Teddy",
        "title": "The stable signature: Rooting watermarks in latent diffusion models"
      }
    ]
  },
  {
    "index": 18,
    "papers": [
      {
        "key": "xiong2023flexible",
        "author": "Xiong, Cheng and Qin, Chuan and Feng, Guorui and Zhang, Xinpeng",
        "title": "Flexible and secure watermarking for latent diffusion model"
      }
    ]
  },
  {
    "index": 19,
    "papers": [
      {
        "key": "wen2023tree",
        "author": "Wen, Yuxin and Kirchenbauer, John and Geiping, Jonas and Goldstein, Tom",
        "title": "Tree-ring watermarks: Fingerprints for diffusion images that are invisible and robust"
      }
    ]
  },
  {
    "index": 20,
    "papers": [
      {
        "key": "zhang2024robust",
        "author": "Zhang, Lijun and Liu, Xiao and Martin, Antoni Viros and Bearfield, Cindy Xiong and Brun, Yuriy and Guan, Hui",
        "title": "Robust Image Watermarking using Stable Diffusion"
      }
    ]
  },
  {
    "index": 21,
    "papers": [
      {
        "key": "an2024benchmarking",
        "author": "An, Bang and Ding, Mucong and Rabbani, Tahseen and Agrawal, Aakriti and Xu, Yuancheng and Deng, Chenghao and Zhu, Sicheng and Mohamed, Abdirisak and Wen, Yuxin and Goldstein, Tom and others",
        "title": "Benchmarking the robustness of image watermarks"
      }
    ]
  },
  {
    "index": 22,
    "papers": [
      {
        "key": "zhao2023recipe",
        "author": "Zhao, Yunqing and Pang, Tianyu and Du, Chao and Yang, Xiao and Cheung, Ngai-Man and Lin, Min",
        "title": "A recipe for watermarking diffusion models"
      }
    ]
  },
  {
    "index": 23,
    "papers": [
      {
        "key": "fernandez2023stable",
        "author": "Fernandez, Pierre and Couairon, Guillaume and J{\\'e}gou, Herv{\\'e} and Douze, Matthijs and Furon, Teddy",
        "title": "The stable signature: Rooting watermarks in latent diffusion models"
      }
    ]
  },
  {
    "index": 24,
    "papers": [
      {
        "key": "xiong2023flexible",
        "author": "Xiong, Cheng and Qin, Chuan and Feng, Guorui and Zhang, Xinpeng",
        "title": "Flexible and secure watermarking for latent diffusion model"
      }
    ]
  },
  {
    "index": 25,
    "papers": [
      {
        "key": "wen2023tree",
        "author": "Wen, Yuxin and Kirchenbauer, John and Geiping, Jonas and Goldstein, Tom",
        "title": "Tree-ring watermarks: Fingerprints for diffusion images that are invisible and robust"
      }
    ]
  },
  {
    "index": 26,
    "papers": [
      {
        "key": "zhang2024robust",
        "author": "Zhang, Lijun and Liu, Xiao and Martin, Antoni Viros and Bearfield, Cindy Xiong and Brun, Yuriy and Guan, Hui",
        "title": "Robust Image Watermarking using Stable Diffusion"
      }
    ]
  },
  {
    "index": 27,
    "papers": [
      {
        "key": "an2024benchmarking",
        "author": "An, Bang and Ding, Mucong and Rabbani, Tahseen and Agrawal, Aakriti and Xu, Yuancheng and Deng, Chenghao and Zhu, Sicheng and Mohamed, Abdirisak and Wen, Yuxin and Goldstein, Tom and others",
        "title": "Benchmarking the robustness of image watermarks"
      }
    ]
  },
  {
    "index": 28,
    "papers": [
      {
        "key": "zhao2023recipe",
        "author": "Zhao, Yunqing and Pang, Tianyu and Du, Chao and Yang, Xiao and Cheung, Ngai-Man and Lin, Min",
        "title": "A recipe for watermarking diffusion models"
      }
    ]
  },
  {
    "index": 29,
    "papers": [
      {
        "key": "fernandez2023stable",
        "author": "Fernandez, Pierre and Couairon, Guillaume and J{\\'e}gou, Herv{\\'e} and Douze, Matthijs and Furon, Teddy",
        "title": "The stable signature: Rooting watermarks in latent diffusion models"
      }
    ]
  },
  {
    "index": 30,
    "papers": [
      {
        "key": "xiong2023flexible",
        "author": "Xiong, Cheng and Qin, Chuan and Feng, Guorui and Zhang, Xinpeng",
        "title": "Flexible and secure watermarking for latent diffusion model"
      }
    ]
  },
  {
    "index": 31,
    "papers": [
      {
        "key": "wen2023tree",
        "author": "Wen, Yuxin and Kirchenbauer, John and Geiping, Jonas and Goldstein, Tom",
        "title": "Tree-ring watermarks: Fingerprints for diffusion images that are invisible and robust"
      }
    ]
  },
  {
    "index": 32,
    "papers": [
      {
        "key": "zhang2024robust",
        "author": "Zhang, Lijun and Liu, Xiao and Martin, Antoni Viros and Bearfield, Cindy Xiong and Brun, Yuriy and Guan, Hui",
        "title": "Robust Image Watermarking using Stable Diffusion"
      }
    ]
  },
  {
    "index": 33,
    "papers": [
      {
        "key": "meng2024latent",
        "author": "Meng, Zheling and Peng, Bo and Dong, Jing",
        "title": "Latent Watermark: Inject and Detect Watermarks in Latent Diffusion Space"
      }
    ]
  },
  {
    "index": 34,
    "papers": [
      {
        "key": "zhao2023invisible",
        "author": "Zhao, Xuandong and Zhang, Kexun and Su, Zihao and Vasan, Saastha and Grishchenko, Ilya and Kruegel, Christopher and Vigna, Giovanni and Wang, Yu-Xiang and Li, Lei",
        "title": "Invisible image watermarks are provably removable using generative ai"
      }
    ]
  },
  {
    "index": 35,
    "papers": [
      {
        "key": "jiang2023evading",
        "author": "Jiang, Zhengyuan and Zhang, Jinghuai and Gong, Neil Zhenqiang",
        "title": "Evading watermark based detection of AI-generated content"
      }
    ]
  },
  {
    "index": 36,
    "papers": [
      {
        "key": "lukas2023leveraging",
        "author": "Lukas, Nils and Diaa, Abdulrahman and Fenaux, Lucas and Kerschbaum, Florian",
        "title": "Leveraging optimization for adaptive attacks on image watermarks"
      }
    ]
  },
  {
    "index": 37,
    "papers": [
      {
        "key": "jiang2023evading",
        "author": "Jiang, Zhengyuan and Zhang, Jinghuai and Gong, Neil Zhenqiang",
        "title": "Evading watermark based detection of AI-generated content"
      }
    ]
  },
  {
    "index": 38,
    "papers": [
      {
        "key": "zhao2023invisible",
        "author": "Zhao, Xuandong and Zhang, Kexun and Su, Zihao and Vasan, Saastha and Grishchenko, Ilya and Kruegel, Christopher and Vigna, Giovanni and Wang, Yu-Xiang and Li, Lei",
        "title": "Invisible image watermarks are provably removable using generative ai"
      }
    ]
  }
]